<Properties StartupConfiguration="{CB078AF7-8CEF-4972-81AC-BD21C3E67408}|Default">
  <MonoDevelop.Ide.ItemProperties.Website PreferredExecutionTarget="/Volumes/Untitled - Data/Applications/Google Chrome.app" />
  <MultiItemStartupConfigurations />
  <MonoDevelop.Ide.Workbench>
    <Pads>
      <Pad Id="ProjectPad">
        <State name="__root__">
          <Node name="WEB" expanded="True">
            <Node name="Website" selected="True" />
          </Node>
        </State>
      </Pad>
    </Pads>
  </MonoDevelop.Ide.Workbench>
  <MonoDevelop.Ide.DebuggingService.PinnedWatches />
  <MonoDevelop.Ide.Workspace ActiveConfiguration="Debug" />
  <MonoDevelop.Ide.DebuggingService.Breakpoints>
    <BreakpointStore />
  </MonoDevelop.Ide.DebuggingService.Breakpoints>
</Properties>